ag_udec/Functions.py
ag_udec/__init__.py
ag_lib_base-0.1.0.dist-info/METADATA
ag_lib_base-0.1.0.dist-info/WHEEL
ag_lib_base-0.1.0.dist-info/top_level.txt
ag_lib_base-0.1.0.dist-info/RECORD
