Metadata-Version: 2.1
Name: ag_lib_base
Version: 0.1.0
Summary: A test library
Home-page: https://github.com/Mo3oDev/ag_lib_base
Author: Miguel Moreno
Author-email: moorenomiguel03@gmail.com
Classifier: Programming Language :: Python :: 3
Classifier: License :: OSI Approved :: MIT License
Classifier: Operating System :: OS Independent
Requires-Python: >=3.6
Requires-Dist: random
